pytest_oof/__init__.py
pytest_oof/__main__.py
pytest_oof/hooks.py
pytest_oof/plugin.py
pytest_oof/utils.py
pytest_oof-1.1.0.dist-info/LICENSE
pytest_oof-1.1.0.dist-info/METADATA
pytest_oof-1.1.0.dist-info/WHEEL
pytest_oof-1.1.0.dist-info/entry_points.txt
pytest_oof-1.1.0.dist-info/top_level.txt
pytest_oof-1.1.0.dist-info/RECORD
