Metadata-Version: 2.1
Name: pytest-oof
Version: 1.1.0
Summary: A Pytest plugin providing structured, programmatic access to a test run's results
Home-page: https://github.com/jeffwright13/pytest-oof
Author: Jeff Wright
Author-email: jeff.washcloth@gmail.com
License: MIT
Keywords: pytest pytest-plugin testing
Classifier: Framework :: Pytest
Classifier: Development Status :: 4 - Beta
Classifier: Intended Audience :: Developers
Classifier: Topic :: Software Development :: Testing
Classifier: Programming Language :: Python :: 3.8
Classifier: Programming Language :: Python :: 3.9
Classifier: Programming Language :: Python :: 3.10
Classifier: Programming Language :: Python :: 3.11
Classifier: Operating System :: OS Independent
Classifier: License :: OSI Approved :: MIT License
Requires-Python: >=3.8
License-File: LICENSE
Requires-Dist: rich >=10.6.0
Requires-Dist: single-source >=0.3.0
Requires-Dist: strip-ansi >=0.1.1
